{
  "205": {
    "rect971" : "rect869"
  },
  "206": {
    "rect971": "rect869"
  },
  "207": {
    "rect971": "rect973"
  },
  "208": {
    "rect867" : "rect971-1"
  },
  "209": {
    "rect975": "rect977",
    "rect867": "rect977"
  },
  "210": {
    "rect975": "rect979",
    "rect867": "rect979"
  },
  "211": {
    "rect975": "rect981",
    "rect867": "rect981"
  },
  "212": {
    "rect975": "rect983",
    "rect867": "rect983"
  },
  "213": {
    "rect975": "rect985",
    "rect867": "rect985"
  },
  "214": {
    "rect975": "rect987",
    "rect867": "rect987"
  },
  "215": {
    "rect975": "rect989",
    "rect867": "rect989"
  },
  "216": {
    "rect975": "rect991",
    "rect867": "rect991"
  },
  "217": {
    "rect867": "rect867"
  },
  "218": {
    "rect855": "rect863",
    "rect867": "rect863"
  },
  "219": {
    "rect867": "rect863",
    "rect855": "rect863"
  },
  "220": {
    "rect867": "rect861",
    "rect855": "rect861"
  },
  "221": {
    "rect867": "rect859",
    "rect855": "rect859"
  },
  "222": {
    "rect867": "rect857",
    "rect855": "rect857"
  },
  "223": {
    "rect975": "rect975"
  },
  "224": {
    "rect975": "rect975"
  },
  "225": {
    "rect975": "rect853",
    "rect837": "rect853"
  },
  "226": {
    "rect975": "rect851",
    "rect837": "rect851"
  },
  "227": {
    "rect975": "rect849",
    "rect837": "rect849"
  },
  "228": {
    "rect975": "rect847",
    "rect837": "rect847"
  },
  "229": {
    "rect975": "rect845",
    "rect837": "rect845"
  },
  "230": {
    "rect975": "rect843",
    "rect837": "rect843"
  },
  "231": {
    "rect837": "rect839"
  },
  "232": {
    "rect837": "rect839"
  },
  "233": {
    "rect837": "rect839"
  },
  "234": {
    "rect837": "rect841"
  },
  "235": {
    "rect837": "rect841"
  },
  "236": {
    "rect837": "rect959",
    "rect855": "rect959"
  },
  "237": {
    "rect837": "rect957",
    "rect855": "rect957"
  },
  "238": {
    "rect837": "rect955",
    "rect855": "rect955"
  },
  "239": {
    "rect837": "rect953",
    "rect855": "rect953"
  },
  "240": {
    "rect837": "rect871",
    "rect855": "rect871"
  },
  "241": {
    "rect837": "rect949",
    "rect855": "rect949"
  },
  "242": {
    "rect837": "rect951",
    "rect855": "rect951"
  },
  "243": {
    "rect855": "rect855"
  },
  "244": {
    "rect855": "rect961"
  },
  "245": {
    "rect855": "rect961"
  },
  "246": {
    "rect855": "rect963"
  },
  "247": {
    "rect855": "rect965"
  },
  "248": {
    "rect855": "rect967"
  },
  "249": {
    "rect855": "rect969"
  },
  "250": {
    "rect855": "rect873",
    "rect917": "rect873"
  },
  "251": {
    "rect855": "rect875",
    "rect917": "rect875"
  },
  "252": {
    "rect917": "rect917"
  },
  "253": {
    "rect887": "rect877",
    "rect917": "rect877"
  },
  "254": {
    "rect887": "rect879",
    "rect917": "rect879"
  },
  "255": {
    "rect887": "rect881",
    "rect917": "rect881"
  },
  "256": {
    "rect887": "rect883",
    "rect917": "rect883"
  },
  "257": {
    "rect887": "rect885",
    "rect917": "rect885"
  },
  "258": {
    "rect887": "rect915"
  },
  "259": {
    "rect887": "rect887"
  },
  "260": {
    "rect887": "rect893",
    "rect913": "rect893"
  },
  "261": {
    "rect913": "rect913"
  },
  "262": {
    "rect913": "rect901",
    "rect903": "rect901"
  },
  "263": {
    "rect903": "rect903"
  },
  "264": {
    "rect947": "rect1003",
    "rect913": "rect1003"
  },
  "265": {
    "rect947": "rect1005",
    "rect913": "rect1005"
  },
  "266": {
    "rect947": "rect1007",
    "rect913": "rect1007"
  },
  "267": {
    "rect947": "rect1009",
    "rect913": "rect1009"
  },
  "268": {
    "rect947": "rect1011",
    "rect913": "rect1011"
  },
  "269": {
    "rect947": "rect1013",
    "rect913": "rect1013"
  },

  "270": {
    "rect887": "rect893",
    "rect913": "rect893"
  },

  "271": {
    "rect887": "rect891",
    "rect913": "rect891"
  },

  "272": {
    "rect887": "rect889",
    "rect913": "rect889"
  },
  "273": {
    "rect917": "rect917"
  },
  "274": {
    "rect855": "rect855"
  },

  "275": {
    "rect867": "rect993",
    "rect947": "rect993"
  },

  "276": {
    "rect867": "rect995",
    "rect947": "rect995"
  },

  "277": {
    "rect867": "rect997",
    "rect947": "rect997"
  },
  "278": {
    "rect867": "rect999",
    "rect947": "rect999"
  },
  "279": {
    "rect867": "rect1001",
    "rect947": "rect1001"
  },
  "280": {
    "rect947": "rect947"
  },
  "281": {
    "rect917": "rect927",
    "rect947": "rect927"
  },
  "282": {
    "rect917": "rect925",
    "rect947": "rect925"
  },
  "283": {
    "rect917": "rect923",
    "rect947": "rect923"
  },
  "284": {
    "rect917": "rect921",
    "rect947": "rect921"
  },
  "285": {
    "rect917": "rect919",
    "rect947": "rect919"
  },
  "286": {
    "rect903": "rect911",
    "rect937": "rect911"
  },
  "287": {
    "rect903": "rect909",
    "rect937": "rect909"
  },
  "288": {
    "rect903": "rect909-0",
    "rect937": "rect909-0"
  },
  "289": {
    "rect903": "rect907",
    "rect937": "rect907"
  },
  "290": {
    "rect903": "rect905",
    "rect937": "rect905"
  },
  "291": {
    "rect903": "rect899",
    "rect913": "rect899"
  },
  "292": {
    "rect903": "rect897",
    "rect913": "rect897"
  },
  "293": {
    "rect903": "rect897-2",
    "rect913": "rect897-2"
  },
  "294": {
    "rect937": "rect945",
    "rect971": "rect945"
  },
  "295": {
    "rect937": "rect943",
    "rect971": "rect943"
  },
  "296": {
    "rect937": "rect941",
    "rect971": "rect941"
  },
  "297": {
    "rect937": "rect939",
    "rect971": "rect939"
  },
  "298": {
    "rect937": "rect937"
  },
  "299": {
    "rect937": "rect935",
    "rect947": "rect935"
  },
  "300": {
    "rect937": "rect933",
    "rect947": "rect933"
  },
  "301": {
    "rect937": "rect931",
    "rect947": "rect931"
  },
  "302": {
    "rect937": "rect929",
    "rect947": "rect929"
  }
}